goose/__init__.py
goose/_logger.py
goose/build.py
goose/notifier.py
goose/profile.py
goose/system.jinja
goose/view.py
goose/cli/__init__.py
goose/cli/config.py
goose/cli/main.py
goose/cli/session.py
goose/cli/session_notifier.py
goose/cli/prompt/__init__.py
goose/cli/prompt/completer.py
goose/cli/prompt/create.py
goose/cli/prompt/goose_prompt_session.py
goose/cli/prompt/lexer.py
goose/cli/prompt/overwrite_session_prompt.py
goose/cli/prompt/prompt_validator.py
goose/cli/prompt/user_input.py
goose/command/__init__.py
goose/command/base.py
goose/command/file.py
goose/synopsis/bash.py
goose/synopsis/developer.md
goose/synopsis/moderator.py
goose/synopsis/plan.md
goose/synopsis/process_manager.py
goose/synopsis/summarize.md
goose/synopsis/synopsis.md
goose/synopsis/system.py
goose/synopsis/text_editor.py
goose/synopsis/toolkit.py
goose/synopsis/util.py
goose/toolkit/__init__.py
goose/toolkit/base.py
goose/toolkit/developer.py
goose/toolkit/github.py
goose/toolkit/jira.py
goose/toolkit/lint.py
goose/toolkit/reasoner.py
goose/toolkit/screen.py
goose/toolkit/utils.py
goose/toolkit/web_browser.py
goose/toolkit/prompts/browser.jinja
goose/toolkit/prompts/developer.jinja
goose/toolkit/prompts/github.jinja
goose/toolkit/prompts/jira.jinja
goose/toolkit/prompts/reasoner.jinja
goose/toolkit/repo_context/__init__.py
goose/toolkit/repo_context/repo_context.py
goose/toolkit/repo_context/utils.py
goose/toolkit/repo_context/prompts/repo_context.jinja
goose/toolkit/summarization/__init__.py
goose/toolkit/summarization/summarize_file.py
goose/toolkit/summarization/summarize_project.py
goose/toolkit/summarization/summarize_repo.py
goose/toolkit/summarization/utils.py
goose/utils/__init__.py
goose/utils/_cost_calculator.py
goose/utils/_create_exchange.py
goose/utils/ask.py
goose/utils/autocomplete.py
goose/utils/file_utils.py
goose/utils/session_file.py
goose/utils/shell.py
goose/utils/time_utils.py
goose_ai-0.9.11.dist-info/METADATA
goose_ai-0.9.11.dist-info/WHEEL
goose_ai-0.9.11.dist-info/entry_points.txt
goose_ai-0.9.11.dist-info/licenses/LICENSE
goose_ai-0.9.11.dist-info/RECORD
