Metadata-Version: 2.3
Name: goose-ai
Version: 0.9.11
Summary: a programming agent that runs on your machine
License-File: LICENSE
Requires-Python: >=3.10
Requires-Dist: ai-exchange==0.9.9
Requires-Dist: attrs>=23.2.0
Requires-Dist: beautifulsoup4>=4.9.3
Requires-Dist: click>=8.1.7
Requires-Dist: keyring>=25.4.1
Requires-Dist: langfuse>=2.38.2
Requires-Dist: prompt-toolkit>=3.0.47
Requires-Dist: pyshadow<=0.0.5
Requires-Dist: rich>=13.7.1
Requires-Dist: ruamel-yaml>=0.18.6
Requires-Dist: selenium>=4.0.0
